{
  "type": "Prerender",
  "expiration": false,
  "group": 16,
  "bypassToken": "a0ba0dd2754effd6b8bd6364d048b3d0",
  "experimentalBypassFor": [
    {
      "type": "header",
      "key": "Next-Action"
    },
    {
      "type": "header",
      "key": "content-type",
      "value": "multipart/form-data;.*"
    }
  ],
  "fallback": {
    "type": "FileFsRef",
    "mode": 33188,
    "fsPath": "activities.prerender-fallback.html"
  },
  "initialHeaders": {
    "x-next-cache-tags": "_N_T_/layout,_N_T_/activities/layout,_N_T_/activities/page,_N_T_/activities"
  },
  "allowQuery": []
}
